setup.py
dumblr/__init__.py
dumblr/cli.py
dumblr/core.py
dumblr/exceptions.py
dumblr/tumblr.py
dumblr/utils.py
dumblr.egg-info/PKG-INFO
dumblr.egg-info/SOURCES.txt
dumblr.egg-info/dependency_links.txt
dumblr.egg-info/entry_points.txt
dumblr.egg-info/requires.txt
dumblr.egg-info/top_level.txt