Metadata-Version: 1.0
Name: dumblr
Version: 1.0
Summary: tumblr for devs
Home-page: https://github.com/devty1023/dumblr
Author: Daniel Y Lee
Author-email: devty1023@gmail.com
License: MIT
Platform: UNKNOWN
